LICENSE
LICENSE.txt
README.rst
setup.cfg
setup.py
madookan/__init__.py
madookan/madoo.py
madookan.egg-info/PKG-INFO
madookan.egg-info/SOURCES.txt
madookan.egg-info/dependency_links.txt
madookan.egg-info/top_level.txt